jrotatelog/__init__.py
jrotatelog/handler.py
jrotatelog-0.1.0.dist-info/LICENSE
jrotatelog-0.1.0.dist-info/METADATA
jrotatelog-0.1.0.dist-info/WHEEL
jrotatelog-0.1.0.dist-info/entry_points.txt
jrotatelog-0.1.0.dist-info/RECORD
