Metadata-Version: 2.1
Name: jrotatelog
Version: 0.1.0
Summary: Rotate logs with incremental generation numbers
Author: Stephen Ferrari
Author-email: stephen.ferrari14@gmail.com
Requires-Python: >=3.11,<4.0
Classifier: Programming Language :: Python :: 3
Classifier: Programming Language :: Python :: 3.11
Classifier: Programming Language :: Python :: 3.12
